pycounts_mn24/__init__.py
pycounts_mn24/plotting.py
pycounts_mn24/pycounts_mn24.py
pycounts_mn24/zen.txt
pycounts_mn24-0.1.0.dist-info/LICENSE
pycounts_mn24-0.1.0.dist-info/METADATA
pycounts_mn24-0.1.0.dist-info/WHEEL
pycounts_mn24-0.1.0.dist-info/RECORD
