Metadata-Version: 2.1
Name: pycounts_mn24
Version: 0.1.0
Summary: Calculating word counts in a new text file.
License: MIT
Author: Mohammad Norouzi
Requires-Python: >=3.9
Classifier: License :: OSI Approved :: MIT License
Classifier: Programming Language :: Python :: 3
Classifier: Programming Language :: Python :: 3.9
Classifier: Programming Language :: Python :: 3.10
Classifier: Programming Language :: Python :: 3.11
Classifier: Programming Language :: Python :: 3.12
Requires-Dist: matplotlib (>=3.4.3)
